LICENSE
README.md
pyproject.toml
setup.cfg
setup.py
src/WikiFiller/WikiFiller.py
src/WikiFiller/__init__.py
src/WikiFiller/lib/Browser.py
src/WikiFiller/lib/Category.py
src/WikiFiller/lib/Functions.py
src/WikiFiller/lib/Globals.py
src/WikiFiller/lib/Template.py
src/WikiFiller/lib/__init__.py
src/WikiFinder/WikiFinder.py
src/WikiFinder/__init__.py
src/WikiFinder/lib/Browser.py
src/WikiFinder/lib/Functions.py
src/WikiFinder/lib/__init__.py
src/wiki_tools.egg-info/PKG-INFO
src/wiki_tools.egg-info/SOURCES.txt
src/wiki_tools.egg-info/dependency_links.txt
src/wiki_tools.egg-info/entry_points.txt
src/wiki_tools.egg-info/requires.txt
src/wiki_tools.egg-info/top_level.txt