Metadata-Version: 2.1
Name: wiki-tools
Version: 1.0.10
Summary: A collections for tools helping wikipedia editing
Home-page: https://github.com/machinexa2/WikiTools
Author: Machine Yadav
Author-email: machinexa@gmail.com
License: MIT
Download-URL: https://github.com/machinexa2/WikiTools/archive/refs/tags/v1.0.4.tar.gz
Keywords: wikipeia,template,automatic,tools
Platform: UNKNOWN
Classifier: Programming Language :: Python :: 3
Classifier: License :: OSI Approved :: MIT License
Classifier: Operating System :: OS Independent
Requires-Python: >=3.8
